itkwasm_morphological_contour_interpolation_wasi/__init__.py
itkwasm_morphological_contour_interpolation_wasi/_version.py
itkwasm_morphological_contour_interpolation_wasi/morphological_contour_interpolation.py
itkwasm_morphological_contour_interpolation_wasi/wasm_modules/morphological-contour-interpolation.wasi.wasm
itkwasm_morphological_contour_interpolation_wasi-2.0.0.dist-info/METADATA
itkwasm_morphological_contour_interpolation_wasi-2.0.0.dist-info/WHEEL
itkwasm_morphological_contour_interpolation_wasi-2.0.0.dist-info/RECORD
